{
  "games": [
    {
      "id": "sample-clicker",
      "name": "Sample Clicker",
      "tagline": "A tiny demo game that proves the shared scaffold works end to end.",
      "themeColor": "#2f3b52",
      "icon": "games/sample-clicker/icons/icon.svg"
    },
    {
      "id": "hypergolic-hull",
      "name": "Hypergolic Hull",
      "tagline": "A hull lot of fun",
      "themeColor": "#2f3b52",
      "icon": "games/hypergolic-hull/icons/icon.svg"
    },
    {
      "id": "trebor",
      "name": "TREEBOAR",
      "tagline": "A good dog vs. a dungeon full of cats — deck-builder combat",
      "themeColor": "#2f3b52",
      "icon": "games/trebor/icons/icon.svg"
    },
    {
      "id": "trace",
      "name": "Step in the Cat",
      "tagline": "Climb the stairs, grab the pins, don't step on the cat.",
      "themeColor": "#5a7a8c",
      "icon": "games/trace/icons/icon.svg"
    },
    {
      "id": "buffer",
      "name": "Buff Up",
      "tagline": "Get gains while loose tum.",
      "themeColor": "#2f3b52",
      "icon": "games/buffer/icons/icon.svg"
    }
  ]
}
